{
  "appPageId" : "69aa2e0f-3f24-49c1-9736-ce34e2f85976",
  "componentName" : "siteforce:sldsOneColLayout",
  "dataProviders" : [ ],
  "id" : "92d7f59b-6aef-4200-8be8-581031327781",
  "label" : "Action Plan Template List",
  "regions" : [ {
    "id" : "b4d01002-8379-4c46-8c7a-c8ceaf20c46a",
    "regionName" : "header",
    "type" : "region"
  }, {
    "components" : [ {
      "componentAttributes" : {
        "enableInlineEdit" : true,
        "filterName" : "{!filterId}",
        "layout" : "FULL",
        "pageSize" : 25,
        "scope" : "{!objectName}",
        "showActionBar" : true,
        "showChartsPanel" : true,
        "showDisplay" : "showall",
        "showFilterPanel" : true,
        "showImageIcon" : true,
        "showManualRefreshButton" : true,
        "showObjectName" : true,
        "showPinnedList" : true,
        "showSearchBar" : true
      },
      "componentName" : "forceCommunity:objectHome",
      "id" : "afd9ec78-ea3a-4d3f-97de-0db6bf3f14fa",
      "renderPriority" : "NEUTRAL",
      "renditionMap" : { },
      "type" : "component"
    } ],
    "id" : "4cdb2dbe-365d-4156-8cb9-9d9d537da11a",
    "regionName" : "content",
    "type" : "region"
  }, {
    "id" : "9c0e61c9-64d8-4f30-aef8-65fc1c7db48e",
    "regionName" : "footer",
    "type" : "region"
  } ],
  "themeLayoutType" : "Inner",
  "type" : "view",
  "viewType" : "list-0PR"
}